kanalizer-0.1.1.dist-info/METADATA
kanalizer-0.1.1.dist-info/WHEEL
kanalizer-0.1.1.dist-info/licenses/LICENSE
kanalizer-0.1.1.dist-info/licenses/NOTICE.md
kanalizer/py.typed
kanalizer/_error.py
kanalizer/_rust.pyi
kanalizer/__init__.py
kanalizer/_rust.pyd
kanalizer-0.1.1.dist-info/RECORD
