Metadata-Version: 2.4
Name: kanalizer
Version: 0.1.1
Classifier: Programming Language :: Rust
Classifier: Programming Language :: Python :: Implementation :: CPython
License-File: LICENSE
License-File: NOTICE.md
Summary: 英単語から読みへの変換を行うライブラリ
License: MIT
Requires-Python: >=3.9
Project-URL: Source Code, https://github.com/VOICEVOX/kanalizer
